mpesa_integration/__init__.py
mpesa_integration/config.py
mpesa_integration/exceptions.py
mpesa_integration/mpesa.py
tests/__init__.py
tests/test.py
tests/test_mpesa.py
mpesa_integration-0.1.0.dist-info/METADATA
mpesa_integration-0.1.0.dist-info/WHEEL
mpesa_integration-0.1.0.dist-info/top_level.txt
mpesa_integration-0.1.0.dist-info/RECORD
